kubunconfector/__init__.py
kubunconfector/kubuntypes.py
kubunconfector/misc.py
kubunconfector/ziptray.py
KubunConfector-0.1.3.post9.dist-info/LICENSE
KubunConfector-0.1.3.post9.dist-info/METADATA
KubunConfector-0.1.3.post9.dist-info/WHEEL
KubunConfector-0.1.3.post9.dist-info/top_level.txt
KubunConfector-0.1.3.post9.dist-info/RECORD
